Workbook

Sheet Matriz Ckeck LIst
C3: MATRIZ PARA COMPROBACIÓN REQUERIMIENTOS DE CALIDAD DE PROYECTO ACADEMICO
D5: SISTEMA: | E5: SISTEMA WEB DE GESTIÓN DE EXPENSAS DEL CONJUNTO LA PRIMAVERA
B7: Nº | C7: CRITERIOS DE CALIDAD (Documento/Requerimientos) | E7: Status Nivel de Acuerdo | F7: CU-01. Administrar Sistema (Nivel 0) | G7: Status Nivel de Acuerdo | H7: CU-02: Gestionar Copropietarios (Nivel 0) | I7: Status Nivel de Acuerdo | J7: CU-03: Implementar Pagos (Nivel 0)
B9: 1 | C9: Agreed | E9: OK | F9: Es fundamental para el control de seguridad solicitado por el Administrador. | G9: OK | H9: Validado por la necesidad de centralizar la base de datos de 60 casas. | I9: OK | J9: Es el objetivo central del negocio y la razón de ser del sistema para el Conjunto La Primavera.
B10: 2 | C10: Ranked | E10: OK | F10: Clasificado como Must Have (M) en tu matriz MoSCoW. | G10: OK | H10: Prioridad Must Have (M); es la base de datos principal. | I10: OK | J10: Prioridad Crítica (Must Have) en la matriz de valor de negocio.
B11: 3 | C11: Unambiguos | E11: OK | F11: Define claramente que gestiona acceso, autenticación y perfiles. | G11: OK | H11: Define operaciones de carga, modificación, eliminación y consulta. | I11: OK | J11: Define claramente que el proceso abarca registro, validación y control de mora.
B12: 4 | C12: Valid and up-to date | E12: NOK | F12: No se han realizado actualizaciones, la última interacción con el cliente fue 08/12/2025 | G12: NOK | H12: No se han realizado actualizaciones, la última interacción con el cliente fue 08/12/2025 | I12: NOK | J12: No se han realizado actualizaciones, la última interacción con el cliente fue 08/12/2025
B13: 5 | C13: Correct | E13: OK | F13: Cubre la necesidad de jerarquía entre Administrador y Copropietario. | G13: NOK | H13: El sistema permite "Eliminar" (CU-2.5), pero el CU-02 no define si esa eliminación es física o lógica, poniendo en riesgo la integridad de la base de datos. | I13: OK | J13: El requerimiento refleja con exactitud la regla de negocio del Conjunto para el procesamiento de pagos esto porque define lógicamente las operaciones financieras necesarias (registro de expensas, validación y cálculo de mora) sin errores conceptuales, garantizando que el sistema calculará y registrará las transacciones tal como lo requiere la administración.
B14: 6 | C14: Consisten | E14: OK | F14: No contradice otros requisitos; es la base de la seguridad. | G14: OK | H14: Se alinea con la lógica de que un Copropietario solo ve sus datos. | I14: OK | J14: Se alinea con los requerimientos no funcionales de integridad de datos (RNF-02).
B15: 7 | C15: Verifiable | E15: OK | F15: Se verifica mediante pruebas de caja negra (login exitoso/fallido). | G15: OK | H15: Se verifica al probar los sub-casos (2.1 al 2.5). | I15: NOK | J15: Al ser un nivel 0, no es verificable por sí mismo si no se prueban todos sus niveles inferiores (3.1 al 3.4).
B16: 8 | C16: Realizable | E16: NOK | F16: El uso de sesiones y perfiles es estándar en desarrollo web pero no se ha establecido un presupuesto y que tenga conocimiento el cliente | G16: NOK | H16: Es un módulo CRUD (Create, Read, Update, Delete) estándar, pero no se ha establecido un presupuesto y que tenga conocimiento el cliente | I16: NOK | J16: Es totalmente factible con una arquitectura web estándar de base de datos relacional, pero no se ha establecido un presupuesto y que tenga conocimiento el cliente
B17: 9 | C17: Traceable | E17: OK | F17: ID: RF-01, vinculado a los sub-procesos 1.1, 1.2 y 1.3. | G17: OK | H17: ID: RF-02. | I17: OK | J17: Código de trazabilidad: RF-03.
B18: 10 | C18: Complete | E18: OK | F18: Describe el propósito, actores y la regla de "mínimo un Administrador". | G18: OK | H18: Describe actores y propósitos generales de manera robusta. | I18: NOK | J18: Incompleto: No define cómo se manejan los pagos realizados en efectivo o si el sistema es estrictamente para transferencias/depósitos.
B19: 11 | C19: Understandability | E19: OK | F19: El lenguaje es claro tanto para el cliente como para el equipo técnico. | G19: OK | H19: Conceptos claros para cualquier usuario del conjunto. | I19: OK | J19: El propósito y la descripción son claros para el cliente y los ingenieros de requisitos.

Sheet MLC CU-02
B1: SISTEMA: | C1: SISTEMA WEB DE GESTION DE EXPENSAS DEL CONJUNTO LA PRIMAVERA
B2: FECHA: | C2: 46126
B3: AUTOR: | C3: Gabriel Manosalvas
B4: REQUERIMIENTO EVALUADO: | C4: CU-02
A6: CONTENIDO
A7: No. | B7: Pregunta | C7: SI | D7: NO
A8: 1 | B8: Todos los requerimientos relevantes se han documentado? | C8: X
A9: 2 | B9: Se han implementado las funciones requeridas? | C9: X
A10: 3 | B10: Existe algún mecanismo que permita seguir el impacto de dicho requerimiento a lo largo del resto de las actividades del ciclo productivo.? | C10: X
A11: 4 | B11: El origen de cada requerimento individual está claro ? | C11: X
A12: 5 | B12: Que tan facil es devolverse a los requerimientos? | C12: X
A13: 6 | B13: Los requerimientos reflejan las necesidades y deseos del cliente? | C13: X
A14: 7 | B14: No hay contradicciones entre los requerimientos? | C14: X
A15: 8 | B15: El requerimiento que se esta especificando contribuye a alcanzar un objetivo definido ? | C15: X
A16: 9 | B16: Existe un proceso acotado (en plazo y presupuesto) que permita determinar que el sistema construido satisface lo descrito en el propio requerimiento? | D16: X
A17: SUMATORIA: | C17: =COUNTA('MLC CU-02'!$C$8:$C$16) -> 8 | D17: =COUNTA('MLC CU-02'!$D$8:$D$16) -> 1
A18: PORCENTAJE : | C18: =C17/9 -> 0.88888889 | D18: =D17/9 -> 0.11111111
A20: DOCUMENTACIÓN
A21: No. | B21: Pregunta | C21: SI | D21: NO
A22: 1 | B22: Aplica un estandar para la documetación de requerimiento? | C22: X
A23: 2 | B23: Cumple con la estructura definida por el estandar? | C23: X
A24: 3 | B24: Utiliza un Glosario de términos normalizado? | C24: X
A25: 4 | B25: Los requerimientos Funcionales estan sujetos a una única interpretación? | C25: X
A26: 5 | B26: El modelo aplicado cumple con la sintaxis? | C26: X
A27: SUMATORIA: | C27: =COUNTA('MLC CU-02'!$C$22:$C$26) -> 5 | D27: =COUNTA('MLC CU-02'!$D$22:$D$26) -> 0
A28: PORCENTAJE : | C28: =C27/5 -> 1 | D28: =D27/5 -> 0
A30: NIVEL DE ACUERDO
A31: No. | B31: Pregunta | C31: SI | D31: NO
A32: 1 | B32: Todos los requerimientos han sido acordados con todos los interesados? | C32: X
A33: 2 | B33: Todos los requerimientos modificados han sido acordados por todos los implicados? | D33: x
A34: 3 | B34: Han sido resueltos todos los conflictos conocidos respectos de los requerimientos? | D34: x
A35: SUMATORIA: | C35: =COUNTA('MLC CU-02'!$C$32:$C$34) -> 1 | D35: =COUNTA('MLC CU-02'!$D$32:$D$34) -> 2
A36: PORCENTAJE : | C36: =C35/3 -> 0.33333333 | D36: =D35/3 -> 0.66666667
A40: RESUMEN
B41: CONTENIDO | C41: 89
B42: DOCUMENTACIÓN | C42: 100
B43: NIVEL DE ACUERDO | C43: 100

Sheet MLC CU-03
B1: SISTEMA: | C1: SISTEMA WEB DE GESTION DE EXPENSAS DEL CONJUNTO LA PRIMAVERA
B2: FECHA: | C2: 46126
B3: AUTOR: | C3: Díaz Stiven
B4: REQUERIMIENTO EVALUADO: | C4: CU-03
A6: CONTENIDO
A7: No. | B7: Pregunta | C7: SI | D7: NO
A8: 1 | B8: Todos los requerimientos relevantes se han documentado? | C8: X
A9: 2 | B9: Se han implementado las funciones requeridas? | C9: X
A10: 3 | B10: Existe algún mecanismo que permita seguir el impacto de dicho requerimiento a lo largo del resto de las actividades del ciclo productivo.? | C10: X
A11: 4 | B11: El origen de cada requerimento individual está claro ? | C11: X
A12: 5 | B12: Que tan facil es devolverse a los requerimientos? | C12: X
A13: 6 | B13: Los requerimientos reflejan las necesidades y deseos del cliente? | C13: X
A14: 7 | B14: No hay contradicciones entre los requerimientos? | C14: X
A15: 8 | B15: El requerimiento que se esta especificando contribuye a alcanzar un objetivo definido ? | C15: X
A16: 9 | B16: Existe un proceso acotado (en plazo y presupuesto) que permita determinar que el sistema construido satisface lo descrito en el propio requerimiento? | D16: X
A17: SUMATORIA: | C17: =COUNTA('MLC CU-03'!$C$8:$C$16) -> 8 | D17: =COUNTA('MLC CU-03'!$D$8:$D$16) -> 1
A18: PORCENTAJE : | C18: =C17/9 -> 0.88888889 | D18: =D17/9 -> 0.11111111
A20: DOCUMENTACIÓN
A21: No. | B21: Pregunta | C21: SI | D21: NO
A22: 1 | B22: Aplica un estandar para la documetación de requerimiento? | C22: X
A23: 2 | B23: Cumple con la estructura definida por el estandar? | C23: X
A24: 3 | B24: Utiliza un Glosario de términos normalizado? | C24: X
A25: 4 | B25: Los requerimientos Funcionales estan sujetos a una única interpretación? | C25: X
A26: 5 | B26: El modelo aplicado cumple con la sintaxis? | C26: X
A27: SUMATORIA: | C27: =COUNTA('MLC CU-03'!$C$22:$C$26) -> 5 | D27: =COUNTA('MLC CU-03'!$D$22:$D$26) -> 0
A28: PORCENTAJE : | C28: =C27/5 -> 1 | D28: =D27/5 -> 0
A30: NIVEL DE ACUERDO
A31: No. | B31: Pregunta | C31: SI | D31: NO
A32: 1 | B32: Todos los requerimientos han sido acordados con todos los interesados? | C32: X
A33: 2 | B33: Todos los requerimientos modificados han sido acordados por todos los implicados? | D33: x
A34: 3 | B34: Han sido resueltos todos los conflictos conocidos respectos de los requerimientos? | D34: x
A35: SUMATORIA: | C35: =COUNTA('MLC CU-03'!$C$32:$C$34) -> 1 | D35: =COUNTA('MLC CU-03'!$D$32:$D$34) -> 2
A36: PORCENTAJE : | C36: =C35/3 -> 0.33333333 | D36: =D35/3 -> 0.66666667
A40: RESUMEN
B41: CONTENIDO | C41: 89
B42: DOCUMENTACIÓN | C42: 100
B43: NIVEL DE ACUERDO | C43: 100

Sheet MLC CU-01
B1: SISTEMA: | C1: SISTEMA WEB DE GESTION DE EXPENSAS DEL CONJUNTO LA PRIMAVERA
B2: FECHA: | C2: 46126
B3: AUTOR: | C3: Jose Leiton
B4: REQUERIMIENTO EVALUADO: | C4: CU-01
A6: CONTENIDO
A7: No. | B7: Pregunta | C7: SI | D7: NO
A8: 1 | B8: Todos los requerimientos relevantes se han documentado? | C8: X
A9: 2 | B9: Se han implementado las funciones requeridas? | C9: x
A10: 3 | B10: Existe algún mecanismo que permita seguir el impacto de dicho requerimiento a lo largo del resto de las actividades del ciclo productivo.? | C10: X
A11: 4 | B11: El origen de cada requerimento individual está claro ? | C11: X
A12: 5 | B12: Que tan facil es devolverse a los requerimientos? | C12: X
A13: 6 | B13: Los requerimientos reflejan las necesidades y deseos del cliente? | C13: X
A14: 7 | B14: No hay contradicciones entre los requerimientos? | C14: x
A15: 8 | B15: El requerimiento que se esta especificando contribuye a alcanzar un objetivo definido ? | C15: X
A16: 9 | B16: Existe un proceso acotado (en plazo y presupuesto) que permita determinar que el sistema construido satisface lo descrito en el propio requerimiento? | D16: x
A17: SUMATORIA: | C17: =COUNTA('MLC CU-01'!$C$8:$C$16) -> 8 | D17: =COUNTA('MLC CU-01'!$D$8:$D$16) -> 1
A18: PORCENTAJE : | C18: =C17/9 -> 0.88888889 | D18: =D17/9 -> 0.11111111
A20: DOCUMENTACIÓN
A21: No. | B21: Pregunta | C21: SI | D21: NO
A22: 1 | B22: Aplica un estandar para la documetación de requerimiento? | C22: X
A23: 2 | B23: Cumple con la estructura definida por el estandar? | C23: X
A24: 3 | B24: Utiliza un Glosario de términos normalizado? | C24: X
A25: 4 | B25: Los requerimientos Funcionales estan sujetos a una única interpretación? | C25: X
A26: 5 | B26: El modelo aplicado cumple con la sintaxis? | C26: X
A27: SUMATORIA: | C27: =COUNTA('MLC CU-01'!$C$22:$C$26) -> 5 | D27: =COUNTA('MLC CU-01'!$D$22:$D$26) -> 0
A28: PORCENTAJE : | C28: =C27/5 -> 1 | D28: =D27/5 -> 0
A30: NIVEL DE ACUERDO
A31: No. | B31: Pregunta | C31: SI | D31: NO
A32: 1 | B32: Todos los requerimientos han sido acordados con todos los interesados? | C32: X
A33: 2 | B33: Todos los requerimientos modificados han sido acordados por todos los implicados? | D33: x
A34: 3 | B34: Han sido resueltos todos los conflictos conocidos respectos de los requerimientos? | D34: x
A35: SUMATORIA: | C35: =COUNTA('MLC CU-01'!$C$32:$C$34) -> 1 | D35: =COUNTA('MLC CU-01'!$D$32:$D$34) -> 2
A36: PORCENTAJE : | C36: =C35/3 -> 0.33333333 | D36: =D35/3 -> 0.66666667
A40: RESUMEN
B41: CONTENIDO | C41: 89
B42: DOCUMENTACIÓN | C42: 100
B43: NIVEL DE ACUERDO | C43: 100

Sheet RECOMENDACIONES
A1: CU-01: Administrar Sistema (Seguridad y Acceso)
A2: No. | B2: PREGUNTA | C2: RECOMENDACIÓN
A3: 1 | B3: ¿Se ha establecido un presupuesto y cronograma formal para el desarrollo de perfiles? | C3: Se debe coordinar una reunión con el cliente para definir el presupuesto asignado, ya que actualmente se marca como "No Realizable" por falta de conocimiento económico del cliente.
A4: 2 | B4: ¿Existe un plan de actualización de requerimientos tras la última revisión de 2025? | C4: Se recomienda actualizar la documentación a la versión actual (2026), ya que la falta de interacción reciente con el cliente pone en riesgo la vigencia del RF-01.
A5: 3 | B5: ¿Se han definido métricas de rendimiento para el proceso de autenticación? | C5: Incorporar criterios de aceptación técnicos (ej. tiempo de respuesta < 2s) para que el CU-01 sea verificable objetivamente más allá de una prueba de caja negra básica.
A7: CU-02: Gestionar Copropietarios (Base de Datos)
A8: No. | B8: PREGUNTA | C8: RECOMENDACIÓN
A9: 1 | B9: ¿La eliminación de copropietarios (CU-2.5) será física o lógica en la base de datos? | C9: Se recomienda implementar eliminación lógica para evitar la pérdida de integridad referencial y asegurar que los registros históricos de deudas no desaparezcan.
A10: 2 | B10: ¿Se ha validado la factibilidad técnica del CRUD frente al presupuesto del proyecto? | C10: Al igual que en el CU-01, es necesario presentar al cliente el costo estimado de implementación de este módulo para que pase de "NOK" a "Realizable".
A11: 3 | B11: ¿Cómo se garantiza que un copropietario solo visualice sus propios datos? | C11: Reforzar en la documentación las reglas de negocio de filtrado de datos por ID de usuario, asegurando la consistencia con la seguridad del sistema.
A13: CU-03: Implementar Pagos (Gestión Financiera)
A14: No. | B14: PREGUNTA | C14: RECOMENDACIÓN
A15: 1 | B15: ¿Cuál es el flujo de trabajo para pagos realizados específicamente en efectivo? | C15: Completar el requerimiento definiendo si el Administrador registrará estos pagos manualmente o si el sistema será exclusivo para transferencias/depósitos.
A16: 2 | B16: ¿Qué mecanismos de prueba se usarán para verificar este CU de Nivel 0? | C16: Debido a que el CU-03 no es verificable por sí mismo, se recomienda hacer pruebas que integren obligatoriamente los sub-procesos 3.1 al 3.4.
A17: 3 | B17: ¿Cómo se gestionará el control de mora del 12% mencionado en la descripción? | C17: Definir la lógica de cálculo automático de intereses dentro del flujo "Ingreso -> Auditoría -> Recibo" para asegurar el cumplimiento del control financiero esperado.
